wwpdb/__init__.py
wwpdb/utils/__init__.py
wwpdb/utils/emdb/EmdbSchema.py
wwpdb/utils/emdb/__init__.py
wwpdb/utils/emdb/cif_emdb_translator/README.md
wwpdb/utils/emdb/cif_emdb_translator/__init__.py
wwpdb/utils/emdb/cif_emdb_translator/cif_emdb_translator.py
wwpdb/utils/emdb/cif_emdb_translator/em_emd_conversion.py
wwpdb/utils/emdb/cif_emdb_translator/emdb.py
wwpdb/utils/emdb/cif_emdb_translator/generatedsnamespaces.py
wwpdb/utils/emdb/cif_emdb_translator/simple_test.py
wwpdb/utils/emdb/cif_emdb_translator/test_cif_to_xml_translator.py
wwpdb/utils/emdb/data/emdb-v3.xsd
wwpdb/utils/emdb/emdb_xml2cif_translator/README.md
wwpdb/utils/emdb/emdb_xml2cif_translator/__init__.py
wwpdb/utils/emdb/emdb_xml2cif_translator/input_files/__init__.py
wwpdb/utils/emdb/emdb_xml2cif_translator/input_files/emdb-xml2cif-mappings.txt
wwpdb/utils/emdb/emdb_xml2cif_translator/tests/__init__.py
wwpdb/utils/emdb/emdb_xml2cif_translator/tests/integration_tests/__init__.py
wwpdb/utils/emdb/emdb_xml2cif_translator/tests/integration_tests/test_xml_to_cif_translator.py
wwpdb/utils/emdb/emdb_xml2cif_translator/tests/unit_tests/__init__.py
wwpdb/utils/emdb/emdb_xml2cif_translator/tests/unit_tests/test_emdbxml2ciftranslator.py
wwpdb/utils/emdb/emdb_xml2cif_translator/translator_classes/CIF.py
wwpdb/utils/emdb/emdb_xml2cif_translator/translator_classes/EMDBMetadata.py
wwpdb/utils/emdb/emdb_xml2cif_translator/translator_classes/EMDBXmlToCifTranslator.py
wwpdb/utils/emdb/emdb_xml2cif_translator/translator_classes/LoggingUtil.py
wwpdb/utils/emdb/emdb_xml2cif_translator/translator_classes/Mappings.py
wwpdb/utils/emdb/emdb_xml2cif_translator/translator_classes/__init__.py
wwpdb.utils.emdb-0.20.dist-info/METADATA
wwpdb.utils.emdb-0.20.dist-info/WHEEL
wwpdb.utils.emdb-0.20.dist-info/entry_points.txt
wwpdb.utils.emdb-0.20.dist-info/top_level.txt
wwpdb.utils.emdb-0.20.dist-info/RECORD
