Metadata-Version: 2.1
Name: wwpdb.utils.emdb
Version: 0.20
Summary: wwPDB EMDB to XML converter
Home-page: https://github.com/rcsb/py-wwpdb_utils_config
Author: Ezra Peisach
Author-email: ezra.peisach@rcsb.org
License: Apache 2.0
Platform: UNKNOWN
Classifier: Development Status :: 3 - Alpha
Classifier: Intended Audience :: Developers
Classifier: Natural Language :: English
Classifier: License :: OSI Approved :: Apache Software License
Classifier: Programming Language :: Python
Classifier: Programming Language :: Python :: 2.7
Classifier: Programming Language :: Python :: 3
Classifier: Programming Language :: Python :: 3.6
Classifier: Programming Language :: Python :: 3.7
Requires-Dist: lxml
Requires-Dist: mmcif
Requires-Dist: wwpdb.utils.config (>=0.22.2)
Provides-Extra: dev
Requires-Dist: check-manifest ; extra == 'dev'
Provides-Extra: test
Requires-Dist: coverage ; extra == 'test'
